pup/__init__.py
pup/__main__.py
pup/api.py
pup/context.py
pup/dispatcher.py
pup/logs.py
pup/spawn.py
pup/plugins/__init__.py
pup/plugins/dirs.py
pup/plugins/download.py
pup/plugins/install_cleanup.py
pup/plugins/metadata.py
pup/plugins/pip_install.py
pup/plugins/python_runtime.py
pup/plugins/linux/__init__.py
pup/plugins/linux/appdir_create.py
pup/plugins/linux/appdir_layout.py
pup/plugins/linux/dirs.py
pup/plugins/linux/steps.py
pup/plugins/linux/appdir_template/__init__.py
pup/plugins/linux/appdir_template/{{cookiecutter.nice_name}}.AppDir/AppRun
pup/plugins/linux/appdir_template/{{cookiecutter.nice_name}}.AppDir/{{cookiecutter.nice_name}}.desktop
pup/plugins/linux/appdir_template/{{cookiecutter.nice_name}}.AppDir/usr/.gitignore
pup/plugins/mac/__init__.py
pup/plugins/mac/app_bundle.py
pup/plugins/mac/create_dmg.py
pup/plugins/mac/dirs.py
pup/plugins/mac/icon_from_png.py
pup/plugins/mac/launcher.py
pup/plugins/mac/notarize.py
pup/plugins/mac/sign.py
pup/plugins/mac/steps.py
pup/plugins/mac/app_bundle_template/__init__.py
pup/plugins/mac/app_bundle_template/cookiecutter.json
pup/plugins/mac/app_bundle_template/{{cookiecutter.app_bundle_name}}.app/Contents/Info.plist
pup/plugins/mac/app_bundle_template/{{cookiecutter.app_bundle_name}}.app/Contents/MacOS/launcher.c
pup/plugins/mac/app_bundle_template/{{cookiecutter.app_bundle_name}}.app/Contents/Resources/.gitignore
pup/plugins/mac/dmgbuild_settings_template/__init__.py
pup/plugins/mac/dmgbuild_settings_template/{{cookiecutter.app_name}}.dmgbuild/settings.py
pup/plugins/mac/sign_resources/__init__.py
pup/plugins/mac/sign_resources/entitlements.plist
pup/plugins/win/__init__.py
pup/plugins/win/create_msi.py
pup/plugins/win/dirs.py
pup/plugins/win/dist_layout.py
pup/plugins/win/icon_from_png.py
pup/plugins/win/signer.py
pup/plugins/win/steps.py
pup/plugins/win/dist_layout_template/__init__.py
pup/plugins/win/dist_layout_template/{{cookiecutter.app_name}} {{cookiecutter.version}}/{{cookiecutter.app_name}}.vbs
pup-1.0.0a17.dist-info/LICENSE
pup-1.0.0a17.dist-info/METADATA
pup-1.0.0a17.dist-info/WHEEL
pup-1.0.0a17.dist-info/entry_points.txt
pup-1.0.0a17.dist-info/top_level.txt
pup-1.0.0a17.dist-info/RECORD
