Metadata-Version: 2.1
Name: pup
Version: 1.0.0a17
Summary: Pluggable Micro Packager
Home-page: https://github.com/mu-editor/pup/
Author: Tiago Montes
Author-email: tiago.montes@gmail.com
Maintainer: Tiago Montes
Maintainer-email: tiago.montes@gmail.com
License: MIT
Keywords: packaging,gui,applications
Classifier: Development Status :: 3 - Alpha
Classifier: Environment :: Console
Classifier: Intended Audience :: Developers
Classifier: License :: OSI Approved :: MIT License
Classifier: Natural Language :: English
Classifier: Operating System :: MacOS
Classifier: Operating System :: Microsoft :: Windows
Classifier: Operating System :: POSIX :: Linux
Classifier: Programming Language :: Python :: 3
Classifier: Programming Language :: Python :: 3.7
Classifier: Programming Language :: Python :: 3.8
Classifier: Topic :: Software Development :: Libraries :: Python Modules
Classifier: Topic :: System :: Installation/Setup
Classifier: Topic :: System :: Software Distribution
Provides-Extra: docs
Provides-Extra: tests
Provides-Extra: release
Provides-Extra: dev
License-File: LICENSE
